GenerateRrr/GenerateRrr.py
GenerateRrr/GenerateRrrPayload.py
GenerateRrr/__init__.py
GetCustomFields/GetCustomField.py
GetCustomFields/GetCustomFieldPayload.py
GetCustomFields/__init__.py
GetListOfBillers/GetBiller.py
GetListOfBillers/GetBillerPayload.py
GetListOfBillers/__init__.py
GetListOfServices/GetService.py
GetListOfServices/GetServicePayload.py
GetListOfServices/__init__.py
GetPaymentStatus/PaymentStatus.py
GetPaymentStatus/PaymentStatusPayload.py
GetPaymentStatus/__init__.py
GetRRRDetails/GetRrrDetail.py
GetRRRDetails/GetRrrDetailPayload.py
GetRRRDetails/__init__.py
PaymentNotification/BillPaymentNotificatiion.py
PaymentNotification/BillerNotificationPayload.py
PaymentNotification/__init__.py
RemitaBillingService/Credentials.py
RemitaBillingService/EncryptionConfig.py
RemitaBillingService/EnvironmentConfig.py
RemitaBillingService/RemitaBillingGateway.py
RemitaBillingService/SetEnvironment.py
RemitaBillingService/__init__.py
Responses/BaseResponse.py
Responses/SdkResponseCode.py
Responses/__init__.py
ValidateRequest/ValidateRequest.py
ValidateRequest/ValidateRequestPayload.py
ValidateRequest/__init__.py
remita_billing_gateway-1.0.1.dist-info/METADATA
remita_billing_gateway-1.0.1.dist-info/WHEEL
remita_billing_gateway-1.0.1.dist-info/top_level.txt
remita_billing_gateway-1.0.1.dist-info/RECORD
