Metadata-Version: 2.1
Name: remita-billing-gateway
Version: 1.0.1
Summary: Python SDK for Remita Billing Gateway Service simple APIs
Home-page: https://github.com/RemitaNet/billing-gateway-sdk-python
Author: SystemSpecs Limited
Author-email: ipgtechnologyteam@gmail.com
License: UNKNOWN
Platform: UNKNOWN
Classifier: Programming Language :: Python :: 3
Classifier: Topic :: Software Development :: Libraries :: Python Modules
Classifier: Topic :: Office/Business :: Financial :: Point-Of-Sale
Classifier: Development Status :: 5 - Production/Stable
Classifier: Operating System :: OS Independent
Requires-Python: >=3.4
